oda_wd_client/__init__.py
oda_wd_client/api.py
oda_wd_client/base/__init__.py
oda_wd_client/base/api.py
oda_wd_client/base/logging.py
oda_wd_client/base/tools.py
oda_wd_client/base/types.py
oda_wd_client/base/utils.py
oda_wd_client/service/__init__.py
oda_wd_client/service/financial_management/__init__.py
oda_wd_client/service/financial_management/api.py
oda_wd_client/service/financial_management/types.py
oda_wd_client/service/financial_management/utils.py
oda_wd_client/service/human_resources/__init__.py
oda_wd_client/service/human_resources/api.py
oda_wd_client/service/human_resources/types.py
oda_wd_client/service/human_resources/utils.py
oda_wd_client/service/resource_management/__init__.py
oda_wd_client/service/resource_management/_base_types.py
oda_wd_client/service/resource_management/api.py
oda_wd_client/service/resource_management/exceptions.py
oda_wd_client/service/resource_management/types.py
oda_wd_client/service/resource_management/utils.py
oda_wd_client/service/staffing/__init__.py
oda_wd_client/service/staffing/api.py
oda_wd_client/service/staffing/types.py
oda_wd_client/service/staffing/utils.py
oda_wd_client/types/__init__.py
oda_wd_client/types/financial_management.py
oda_wd_client/types/human_resources.py
oda_wd_client/types/resource_management.py
oda_wd_client/types/staffing.py
oda_wd_client-0.2.3.dist-info/METADATA
oda_wd_client-0.2.3.dist-info/WHEEL
oda_wd_client-0.2.3.dist-info/RECORD
