Metadata-Version: 2.1
Name: oda-wd-client
Version: 0.2.3
Summary: A library for interacting with Workday from Python
Author: Karl Fredrik Haugland
Author-email: karlfredrik.haugland@oda.com
Requires-Python: >=3.11,<3.12
Classifier: Programming Language :: Python :: 3
Classifier: Programming Language :: Python :: 3.11
Requires-Dist: pre-commit (>=3.3.3,<4.0.0)
Requires-Dist: pydantic (>=2,<3)
Requires-Dist: python-magic (>=0.4.27,<0.5.0)
Requires-Dist: suds-py3 (>=1.4.5.0,<2.0.0.0)
Requires-Dist: yamllint (>=1.32.0,<2.0.0)
